ngen/__init__.py
ngen/cli.py
ngen/scripts/ngen-rancher
ngen_cli-0.1.2.dist-info/METADATA
ngen_cli-0.1.2.dist-info/WHEEL
ngen_cli-0.1.2.dist-info/entry_points.txt
ngen_cli-0.1.2.dist-info/top_level.txt
ngen_cli-0.1.2.dist-info/RECORD
