Metadata-Version: 2.4
Name: ngen-cli
Version: 0.1.2
Summary: Universal command wrapper package that dispatches to /usr/local/bin/ngen-* scripts
Author: ngen contributors
License-Expression: MIT
Keywords: cli,wrapper,command,dispatch
Classifier: Development Status :: 3 - Alpha
Classifier: Intended Audience :: Developers
Classifier: Programming Language :: Python :: 3
Classifier: Programming Language :: Python :: 3.7
Classifier: Programming Language :: Python :: 3.8
Classifier: Programming Language :: Python :: 3.9
Classifier: Programming Language :: Python :: 3.10
Classifier: Programming Language :: Python :: 3.11
Requires-Python: >=3.7
